coinmetrics/__init__.py
coinmetrics/_catalogs.py
coinmetrics/_data_collection.py
coinmetrics/_exceptions.py
coinmetrics/_models.py
coinmetrics/_schema_constants.py
coinmetrics/_typing.py
coinmetrics/_utils.py
coinmetrics/api_client.py
coinmetrics/build.py
coinmetrics/constants.py
coinmetrics/py.typed
coinmetrics/schema_resolver.py
coinmetrics_api_client-2026.1.14.15.dist-info/METADATA
coinmetrics_api_client-2026.1.14.15.dist-info/WHEEL
coinmetrics_api_client-2026.1.14.15.dist-info/entry_points.txt
coinmetrics_api_client-2026.1.14.15.dist-info/licenses/LICENSE
coinmetrics_api_client-2026.1.14.15.dist-info/RECORD
