Metadata-Version: 2.4
Name: coinmetrics-api-client
Version: 2026.1.14.15
Summary: Python client for Coin Metrics API v4.
License: MIT
License-File: LICENSE
Keywords: coin metrics,coin,metrics,crypto,bitcoin,network-data,market-data,api,handy
Author: Coin Metrics
Author-email: info@coinmetrics.io
Requires-Python: >=3.9.0,<4.0.0
Classifier: License :: OSI Approved :: MIT License
Classifier: Programming Language :: Python :: 3
Classifier: Programming Language :: Python :: 3.9
Classifier: Programming Language :: Python :: 3.10
Classifier: Programming Language :: Python :: 3.11
Classifier: Programming Language :: Python :: 3.12
Classifier: Programming Language :: Python :: 3.13
Classifier: Programming Language :: Python :: 3.14
Requires-Dist: PyYAML (>=6.0,<7.0)
Requires-Dist: numpy (>=2.0.0,<3.0.0)
Requires-Dist: orjson (>=3.6.0,<4.0.0)
Requires-Dist: pandas (>=2.0.0,<3.0.0)
Requires-Dist: polars (>=1.0.0,<2.0.0)
Requires-Dist: python-dateutil (>=2.8.2,<3.0.0)
Requires-Dist: requests (>=2.24.0,<3.0.0)
Requires-Dist: tqdm (>=4.64.1,<5.0.0)
Requires-Dist: typer (>=0.7.0)
Requires-Dist: websocket-client (>=1.6.0,<2.0.0)
Project-URL: Documentation, https://coinmetrics.github.io/api-client-python/site/index.html
Project-URL: Homepage, https://coinmetrics.github.io/api-client-python/site/index.html
Project-URL: Repository, https://github.com/coinmetrics/api-client-python
